faceorientationprep/__init__.py
faceorientationprep/exceptions/__init__.py
faceorientationprep/exceptions/exceptions.py
faceorientationprep/faceorientationfixer/__init__.py
faceorientationprep/faceorientationfixer/faceorientationfixer.py
faceorientationprep/orientationclassifier/__init__.py
faceorientationprep/orientationclassifier/orientationclassifier.py
faceorientationprep/utils/__init__.py
faceorientationprep/utils/imageutils.py
face_orientation_prep_natchapolt-0.0.2.dist-info/LICENSE
face_orientation_prep_natchapolt-0.0.2.dist-info/METADATA
face_orientation_prep_natchapolt-0.0.2.dist-info/WHEEL
face_orientation_prep_natchapolt-0.0.2.dist-info/top_level.txt
face_orientation_prep_natchapolt-0.0.2.dist-info/RECORD
