Metadata-Version: 2.1
Name: face-orientation-prep-natchapolt
Version: 0.0.2
Summary: A simple face image orientation pre-processor package
Home-page: https://github.com/natchapolt/face-orientation-prep.git
Author: Natchapol.TH
Author-email: natchapol-t@hotmail.com
License: UNKNOWN
Platform: UNKNOWN
Classifier: Programming Language :: Python :: 3
Classifier: License :: OSI Approved :: MIT License
Classifier: Operating System :: OS Independent
Requires-Dist: aniso8601 (==7.0.0)
Requires-Dist: Click (==7.0)
Requires-Dist: cmake (==3.13.3)
Requires-Dist: cycler (==0.10.0)
Requires-Dist: decorator (==4.4.0)
Requires-Dist: dlib (==19.17.0)
Requires-Dist: Flask (==1.0.3)
Requires-Dist: Flask-RESTful (==0.3.7)
Requires-Dist: gunicorn (==19.9.0)
Requires-Dist: imageio (==2.5.0)
Requires-Dist: itsdangerous (==1.1.0)
Requires-Dist: Jinja2 (==2.10.1)
Requires-Dist: kiwisolver (==1.1.0)
Requires-Dist: MarkupSafe (==1.1.1)
Requires-Dist: matplotlib (==3.1.0)
Requires-Dist: networkx (==2.3)
Requires-Dist: numpy (==1.16.4)
Requires-Dist: opencv-contrib-python (==4.1.0.25)
Requires-Dist: Pillow (==6.0.0)
Requires-Dist: pyparsing (==2.4.0)
Requires-Dist: python-dateutil (==2.8.0)
Requires-Dist: pytz (==2019.1)
Requires-Dist: PyWavelets (==1.0.3)
Requires-Dist: scikit-image (==0.15.0)
Requires-Dist: scipy (==1.3.0)
Requires-Dist: six (==1.12.0)
Requires-Dist: Werkzeug
